{
  "project_info": {
    "project_number": "170744366068",
    "project_id": "chefcito-comidas",
    "storage_bucket": "chefcito-comidas.appspot.com"
  },
  "client": [
    {
      "client_info": {
        "mobilesdk_app_id": "1:170744366068:android:fceb222b2e64f79ee6afa1",
        "android_client_info": {
          "package_name": "chefcito.app"
        }
      },
      "oauth_client": [
        {
          "client_id": "170744366068-0mgs76uf4qhsk041jftg5ufa80tfjhq4.apps.googleusercontent.com",
          "client_type": 1,
          "android_info": {
            "package_name": "chefcito.app",
            "certificate_hash": "5e8f16062ea3cd2c4a0d547876baa6f38cabf625"
          }
        },
        {
          "client_id": "170744366068-hrdaou9sieacr0eg5fui2c23npa2berf.apps.googleusercontent.com",
          "client_type": 3
        }
      ],
      "api_key": [
        {
          "current_key": "AIzaSyDyywY2VXheuHWyAl-rjKQvvMXbsuxu2L8"
        }
      ],
      "services": {
        "appinvite_service": {
          "other_platform_oauth_client": [
            {
              "client_id": "170744366068-hrdaou9sieacr0eg5fui2c23npa2berf.apps.googleusercontent.com",
              "client_type": 3
            },
            {
              "client_id": "170744366068-egrkd2a4o3b1rut83gp60g0lnbnj7f1l.apps.googleusercontent.com",
              "client_type": 2,
              "ios_info": {
                "bundle_id": "chefcito.app"
              }
            }
          ]
        }
      }
    }
  ],
  "configuration_version": "1"
}